tocs/__init__.py
tocs/main.py
tocs-1.0.7.dist-info/licenses/LICENSE
tocs-1.0.7.dist-info/METADATA
tocs-1.0.7.dist-info/WHEEL
tocs-1.0.7.dist-info/entry_points.txt
tocs-1.0.7.dist-info/top_level.txt
tocs-1.0.7.dist-info/RECORD
