Metadata-Version: 2.4
Name: tocs
Version: 1.0.7
Summary: Generate TOC for markdown files
Author-email: Andrea Bondanini <bondaniniandrea@gmail.com>
License: MIT
Project-URL: Homepage, https://github.com/sbundaz/tocs
Project-URL: Repository, https://github.com/sbundaz/tocs
Project-URL: Issues, https://github.com/sbundaz/tocs/issues
Keywords: markdown,tocs,cli,documentation,generator
Requires-Python: >=3.11.9
License-File: LICENSE
Provides-Extra: dev
Requires-Dist: pytest; extra == "dev"
Requires-Dist: black; extra == "dev"
Dynamic: license-file
